webtools/__init__.py
webtools/flask.py
webtools/js.py
webtools/php.py
webtools/xss.py
webctfkit-0.3.0.dist-info/LICENSE
webctfkit-0.3.0.dist-info/METADATA
webctfkit-0.3.0.dist-info/WHEEL
webctfkit-0.3.0.dist-info/RECORD
